{"__type__":"cc.AnimationClip","_name":"duizhansb","_duration":0.7,"sample":10,"curveData":{"paths":{"sb":{"props":{"position":[{"frame":0,"value":[326.3,825.5]}],"scaleX":[{"frame":0,"value":1},{"frame":0.7,"value":3.5}],"scaleY":[{"frame":0,"value":1},{"frame":0.7,"value":3.5}],"opacity":[{"frame":0,"value":255},{"frame":0.7,"value":0}]}},"sbzj":{"props":{"position":[{"frame":0,"value":[559,657]},{"frame":0.6,"value":[456.1,789.2]},{"frame":0.7,"value":[456.1,789.2]}],"scaleX":[{"frame":0,"value":1.9},{"frame":0.5,"value":0.9},{"frame":0.6,"value":1}],"scaleY":[{"frame":0,"value":1.6},{"frame":0.5,"value":0.9},{"frame":0.6,"value":1}]}}}}}